{"side": "s", "boundaries": [882.96751, 884.98546], "photos": [{"id": "75233ff2-f0d4-411d-950f-5c7cad61d62b", "coordinate": 885.73466, "year": 1973}, {"id": "c8310736-cda1-4a0b-8ed8-6404ecde4e06", "coordinate": 885.11121, "year": 1973}, {"id": "3a3d807b-92a9-461d-a1db-ab5d2b6aef0f", "coordinate": 884.48774, "year": 1973}, {"id": "c286ac06-e3ea-413c-b940-50d09a9a65f0", "coordinate": 883.86517, "year": 1973}, {"id": "9a282d02-2862-4cf6-b324-537770b2ecd7", "coordinate": 883.24173, "year": 1973}, {"id": "85ba00d5-2ed6-4d57-b913-c9418bda61e7", "coordinate": 882.61988, "year": 1973}, {"id": "45e413b2-f2f1-457c-ba35-6646600c29e4", "coordinate": 885.54371, "year": 1973}, {"id": "0123b0a5-5c58-453f-87b0-73b2b6f7f334", "coordinate": 884.85244, "year": 1973}, {"id": "a283cb86-499d-4440-af1e-948854f97d38", "coordinate": 883.9915, "year": 1973}, {"id": "dfe65dbb-8d8c-4723-aa91-da674e5334e6", "coordinate": 883.1297, "year": 1973}, {"id": "e82a3d0d-0d78-4e8a-922a-80ca450a28df", "coordinate": 882.26953, "year": 1973}, {"id": "977e5fdb-0557-45cd-90c4-b083d7c6bfe5", "coordinate": 885.71568, "year": 1985}, {"id": "1ec5439b-9c60-42bb-8ce3-c7fce08eafe4", "coordinate": 884.98884, "year": 1985}, {"id": "ea6baf3a-e3c7-4abe-a2c4-ce66a2903c8b", "coordinate": 884.26198, "year": 1985}, {"id": "2bc72fe1-243c-4777-b9eb-3c1b51d83505", "coordinate": 883.53603, "year": 1985}, {"id": "fe88a827-08c3-4e1f-b69e-72bfb31d11a0", "coordinate": 882.81076, "year": 1985}, {"id": "73826e48-7eb0-4fc5-914e-092d69ee67ef", "coordinate": 885.22921, "year": 1995}, {"id": "e5a2a008-d607-4428-86f3-a442764b0ce9", "coordinate": 884.27457, "year": 1995}, {"id": "47af4155-5dc4-4020-8940-23cd7969c6e6", "coordinate": 883.32086, "year": 1995}, {"id": "0123dbe2-86d8-4dd3-aee1-bf5de5dabf06", "coordinate": 882.36788, "year": 1995}, {"id": "011d171b-12ef-4843-9ce2-ff62faabd632", "coordinate": 884.95787, "year": 1995}, {"id": "19d6c869-ae58-4558-a30c-153f49d593a8", "coordinate": 884.00379, "year": 1995}, {"id": "2d123b00-0e61-41fa-b0af-e3de5ad1dee1", "coordinate": 883.05036, "year": 1995}, {"id": "ce08930f-6431-478c-89b0-929ac2b987ab", "coordinate": 885.53178, "year": 2007}, {"id": "4b183941-4062-49b2-86ea-5f100bcb096f", "coordinate": 884.96214, "year": 2007}, {"id": "e0c9531c-af17-41ba-839a-22950ce1dbe7", "coordinate": 884.31031, "year": 2007}, {"id": "12cdddeb-f7e1-4372-a13c-1849ed88d1ed", "coordinate": 883.65938, "year": 2007}, {"id": "ef243c3f-4d5f-4954-9b11-b1fb19a93e8b", "coordinate": 883.00908, "year": 2007}, {"id": "e2629e65-b169-4ae4-878e-5e62b4978041", "coordinate": 882.35738, "year": 2007}], "census_data": {"tracts": {"1960": 1976, "1970": 1976, "1980": 1976, "1990": 1976, "2000": 1976, "2010": 1976}, "total_pop": {"1960": 2867.0, "1970": 1797.0, "1980": 3744.0, "1990": 3395.0, "2000": 2984.0, "2010": 2376.0}, "race_white": {"1960": 0.91, "1970": 0.9, "1980": 0.4, "1990": 0.06, "2000": 0.34, "2010": 0.44}, "race_black": {"1960": 0.004, "1970": 0.002, "1980": 0.004, "1990": 0.004, "2000": 0.01, "2010": 0.02}, "race_span_hisp": {"1960": 0.44, "1970": 0.72, "1980": 0.58, "1990": 0.58, "2000": 0.63, "2010": 0.38}, "educ_hs": {"1960": 0.54, "1970": 0.49, "1980": 0.45, "1990": 0.35, "2000": 0.45, "2010": 0.7}, "educ_college": {"1960": 0.15, "1970": 0.13, "1980": 0.16, "1990": 0.21, "2000": 0.27, "2010": 0.37}, "educ_bach": {"1990": 0.08, "2000": 0.13, "2010": 0.37}, "jobs_pers_entmt": {"1970": 0.06, "1980": 0.1, "1990": 0.07, "2000": 0.14, "2010": 0.12}, "jobs_service": {"1960": 0.16, "1970": 0.14, "1980": 0.14, "1990": 0.2, "2000": 0.23, "2010": 0.15}, "avg_fam_income": {"1970": 7430.0, "1980": 13800.0, "1990": 27600.0, "2000": 36700.0, "2010": 66300.0}, "med_fam_income": {"1970": 5900.0, "1980": 10000.0, "1990": 19500.0, "2000": 26400.0, "2010": 47700.0}, "rented_housing": {"1960": 0.83, "1970": 0.86, "1980": 0.85, "1990": 0.83, "2000": 0.84, "2010": 0.79}, "foreign_born_pop": {"1970": 0.31, "1980": 0.68, "1990": 0.67, "2000": 0.56, "2010": 0.44}, "foreign_noncitizens": {"1970": 0.2, "1990": 0.56, "2000": 0.37, "2010": 0.21}, "foreign_naturalized": {"1970": 0.11, "1990": 0.11, "2000": 0.19, "2010": 0.22}}, "occupants_data": [{"fragment": "", "year": 1987, "entry": "GRANDVIEW PRODUCTIONS"}, {"fragment": "A", "year": 1987, "entry": "J & B TRADING INC"}, {"fragment": "C", "year": 1987, "entry": "ARTCON STUDIO"}, {"fragment": "C", "year": 1987, "entry": "ARTCON GRAPHICS"}], "newspaper_data": [], "social_cultural_data": [], "assessor_data": [{"id": 190, "order": "190.00000000000000000000", "OBJECTID": "1239862", "AIN": "5405027023", "APN": "5405-027-023", "address": "1176", "SitusDirection": "W", "fragment": "", "SitusStreet": "SUNSET BLVD", "SitusAddress": "1176 W SUNSET BLVD", "SitusCity": "LOS ANGELES CA", "SitusZIP": "90012-1243", "SitusFullAddress": "1176 W SUNSET BLVD LOS ANGELES CA 90012", "TaxRateArea": "13", "TaxRateCity": "LOS ANGELES", "AgencyClassNo": "", "AgencyName": "", "AgencyType": "", "UseCode": "3300", "UseCode_2": "33", "UseType": "Industrial", "UseDescription": "Warehousing, Distribution, Storage", "DesignType1": "3300", "YearBuilt1": "1982", "EffectiveYear1": "1982", "Units1": "0", "Bedrooms1": "0", "Bathrooms1": "0", "SQFTmain1": "5265", "DesignType2": "", "YearBuilt2": "", "EffectiveYear2": "", "Units2": "", "Bedrooms2": "", "Bathrooms2": "", "SQFTmain2": "", "DesignType3": "", "YearBuilt3": "", "EffectiveYear3": "", "Units3": "", "Bedrooms3": "", "Bathrooms3": "", "SQFTmain3": "", "DesignType4": "", "YearBuilt4": "", "EffectiveYear4": "", "Units4": "", "Bedrooms4": "", "Bathrooms4": "", "SQFTmain4": "", "DesignType5": "", "YearBuilt5": "", "EffectiveYear5": "", "Units5": "", "Bedrooms5": "", "Bathrooms5": "", "SQFTmain5": "", "Roll_Year": "2021", "Roll_LandValue": "2500000", "Roll_ImpValue": "750000", "Roll_PersPropValue": "0", "Roll_FixtureValue": "0", "Roll_HomeOwnersExemp": "0", "Roll_RealEstateExemp": "0", "Roll_PersPropExemp": "0", "Roll_FixtureExemp": "0", "Roll_LandBaseYear": "2021", "Roll_ImpBaseYear": "2021", "SpatialChangeDate": "", "ParcelCreateDate": "0", "ParcelTypeCode": "0", "Assr_Map": "5405-027", "Assr_Index_Map": "5405-NDX", "QualityClass1": "C6B", "QualityClass2": "", "QualityClass3": "", "QualityClass4": "", "QualityClass5": "", "LegalDescLine1": "*ANGELENO HEIGHTS*(EX. OF ST)", "LegalDescLine2": "", "LegalDescLine3": "", "LegalDescLine4": "", "LegalDescLine5": "", "LegalDescLineLast": "LOT    1 BLK   27", "LegalDescription": "*ANGELENO HEIGHTS*(EX. OF ST) LOT    1 BLK   27"}]}