{"side": "n", "boundaries": [427.08738, 429.7214], "photos": [{"id": "62e78b8b-438c-446e-93e9-02cafe6b80b0", "coordinate": 427.1687, "year": 1973}, {"id": "9889206f-64d2-4029-b8eb-a20489d1aecd", "coordinate": 427.79955, "year": 1973}, {"id": "1c270c03-b701-476b-b83d-ca5066f27776", "coordinate": 428.43041, "year": 1973}, {"id": "0fc9f7ae-2a08-4ca7-acb6-e6cc5447a031", "coordinate": 429.06127, "year": 1973}, {"id": "f675d3bb-130a-492c-9fe6-80aa10497c45", "coordinate": 429.69212, "year": 1973}, {"id": "bd49c14a-5958-464f-b14d-105b88f4383a", "coordinate": 427.18318, "year": 1985}, {"id": "9c317712-5386-4307-b472-89cf01caf043", "coordinate": 427.82083, "year": 1985}, {"id": "2ec82789-0e76-47fd-921e-f57ab66183ec", "coordinate": 428.45849, "year": 1985}, {"id": "bef6473e-4148-4067-b493-18632e405698", "coordinate": 429.09614, "year": 1985}, {"id": "d535fcc0-14ac-4214-9b88-a562d5eeb2f3", "coordinate": 427.18441, "year": 1995}, {"id": "24f7b070-ea29-45e8-8ddc-f67003890dc8", "coordinate": 427.95427, "year": 1995}, {"id": "61723339-0826-4e47-9b48-5a22cca06eaa", "coordinate": 428.72412, "year": 1995}, {"id": "d1e8747f-1d99-4a86-862c-50dee8560a1d", "coordinate": 429.49397, "year": 1995}, {"id": "04ec6412-5f8b-404a-89d8-173dabb51701", "coordinate": 427.22897, "year": 2007}, {"id": "ff1f95a2-45fb-4340-ad35-d27ec7214e63", "coordinate": 427.89872, "year": 2007}, {"id": "8ccaf15a-30b9-4e5d-bfbb-e9c49e75f7a4", "coordinate": 428.56847, "year": 2007}, {"id": "651b3065-8f78-4780-b86f-1d63f8093d9c", "coordinate": 429.23823, "year": 2007}], "census_data": {"tracts": {"1960": 1906, "1970": 1906, "1980": 1906, "1990": 1910, "2000": 1910, "2010": 1910}, "total_pop": {"1960": 3019.0, "1970": 1810.0, "1980": 2325.0, "1990": 3615.0, "2000": 3036.0, "2010": 3228.0}, "race_white": {"1960": 0.98, "1970": 0.93, "1980": 0.64, "1990": 0.69, "2000": 0.45, "2010": 0.44}, "race_black": {"1960": 0.001, "1970": 0.02, "1980": 0.06, "1990": 0.07, "2000": 0.06, "2010": 0.03}, "race_span_hisp": {"1960": 0.04, "1970": 0.14, "1980": 0.28, "1990": 0.61, "2000": 0.6, "2010": 0.58}, "educ_hs": {"1960": 0.77, "1970": 0.84, "1980": 0.85, "1990": 0.63, "2000": 0.54, "2010": 0.72}, "educ_college": {"1960": 0.28, "1970": 0.38, "1980": 0.41, "1990": 0.44, "2000": 0.39, "2010": 0.48}, "jobs_pers_entmt": {"1970": 0.1, "1980": 0.09, "1990": 0.25, "2000": 0.24, "2010": 0.21}, "jobs_service": {"1960": 0.09, "1970": 0.12, "1980": 0.18, "1990": 0.23, "2000": 0.28, "2010": 0.22}, "avg_fam_income": {"1970": 9568.0, "1980": 12000.0, "1990": 23500.0, "2000": 28000.0, "2010": 41300.0}, "med_fam_income": {"1980": 11300.0, "1990": 19500.0, "2000": 21400.0, "2010": 35200.0}, "rented_housing": {"1960": 0.91, "1970": 0.92, "1980": 0.96, "1990": 0.96, "2000": 0.96, "2010": 0.96}, "foreign_born_pop": {"1970": 0.32, "1980": 0.53, "1990": 0.58, "2000": 0.57, "2010": 0.53}, "foreign_noncitizens": {"1970": 0.22, "1990": 0.46, "2000": 0.44, "2010": 0.35}, "foreign_naturalized": {"1970": 0.09, "1990": 0.12, "2000": 0.13, "2010": 0.18}, "educ_bach": {"1990": 0.19, "2000": 0.18, "2010": 0.27}}, "occupants_data": [{"fragment": "", "year": 1965, "entry": "URIE JOHN-ASSOCIATES"}, {"fragment": "", "year": 1973, "entry": "GLICKMAN ZACHARY ARTISTS MANAGEMENT"}, {"fragment": "", "year": 1987, "entry": "COMMUNICOM CABLE TV"}, {"fragment": "", "year": 1973, "entry": "BIZARRE PRODUCTIONS"}, {"fragment": "", "year": 1987, "entry": "HOLLYWOOD TIMES STAGE"}, {"fragment": "", "year": 1973, "entry": "STRAIGHT RECORDS"}, {"fragment": "", "year": 1973, "entry": "BIZARRE PRODUCTIONS"}, {"fragment": "", "year": 1973, "entry": "COHEN HERB MANAGEMENT"}, {"fragment": "", "year": 1973, "entry": "KWANZA RECORDS"}, {"fragment": "", "year": 1973, "entry": "SCHENKEL CAL"}, {"fragment": "", "year": 1973, "entry": "THIRD STORY MUSIC"}], "newspaper_data": [], "social_cultural_data": [], "assessor_data": []}