{"side": "s", "boundaries": [146.43986, 148.93208], "photos": [{"id": "50d3dcd2-defc-469c-9b18-30eef177767f", "coordinate": 148.84718, "year": 1966}, {"id": "aacda5e0-39ee-4c08-bf99-c044d454909a", "coordinate": 148.43454, "year": 1966}, {"id": "cf4f4b2a-6a99-47e8-b606-fe1deb5ff2ed", "coordinate": 148.0219, "year": 1966}, {"id": "b3775640-7ecf-4e87-93a3-1d9d23b96dcf", "coordinate": 147.72251, "year": 1966}, {"id": "6619b3f3-0f46-4325-bf8e-65f1e98ac412", "coordinate": 147.42313, "year": 1966}, {"id": "986cbef5-65f8-4b92-bfa7-6a8f0f95fb6f", "coordinate": 147.12374, "year": 1966}, {"id": "11995152-1aa4-4417-a69b-a7976b5f3511", "coordinate": 146.82435, "year": 1966}, {"id": "4ac05b98-4f96-45b8-92b2-ba7af3d8baa0", "coordinate": 146.52496, "year": 1966}, {"id": "cd512ff0-606c-4050-883a-4f29b93f704b", "coordinate": 148.61076, "year": 1973}, {"id": "ed54511e-4e37-4ae1-b82f-30ae7bb20a7a", "coordinate": 147.93609, "year": 1973}, {"id": "fdde2277-73c3-4546-8064-7158c7a0a97a", "coordinate": 147.41453, "year": 1973}, {"id": "a60618bd-9c00-43b9-b6c6-fa68612906cb", "coordinate": 146.89297, "year": 1973}, {"id": "5b5b365e-05a9-4d56-93bf-785c1b6b646d", "coordinate": 148.57481, "year": 1985}, {"id": "f998e1d8-12f6-40ad-b863-3ef60fb26b21", "coordinate": 147.9346, "year": 1985}, {"id": "75586f10-1a41-4c72-a02d-022a783dc6b2", "coordinate": 147.41535, "year": 1985}, {"id": "67562046-64a7-4f6e-9910-ebc907fd61b5", "coordinate": 146.8961, "year": 1985}, {"id": "3ba39a3c-da6c-4ccb-abd5-f9ae25c79650", "coordinate": 147.96622, "year": 1995}, {"id": "7e316d78-b56f-4b0c-82e1-84e9b010179d", "coordinate": 146.63645, "year": 1995}, {"id": "e58539d1-2ed5-490f-bcb2-af0c3143ebe0", "coordinate": 148.05842, "year": 1995}, {"id": "6fe92c73-697a-44f7-b66a-dbf5b7be1202", "coordinate": 147.35147, "year": 1995}, {"id": "b64fbaa2-1380-4df8-9139-2280fdf98dff", "coordinate": 146.46922, "year": 1995}, {"id": "2fd55785-f2dd-438c-83bb-30f112e3a844", "coordinate": 148.62936, "year": 2007}, {"id": "e80da0ab-075c-4ddd-a022-25fd229e29f9", "coordinate": 147.93609, "year": 2007}, {"id": "a5834131-edf4-4441-bcbd-05ff6b53d5a2", "coordinate": 147.26406, "year": 2007}, {"id": "27857d88-afe6-4996-a84b-80b6289a0beb", "coordinate": 146.59202, "year": 2007}], "census_data": {"tracts": {"1960": 1942, "1970": 1942, "1980": 1942, "1990": 1942, "2000": 1942, "2010": 1942}, "total_pop": {"1960": 4899.0, "1970": 5302.0, "1980": 5092.0, "1990": 4956.0, "2000": 5154.0, "2010": 3588.0}, "race_white": {"1960": 0.98, "1970": 0.97, "1980": 0.94, "1990": 0.94, "2000": 0.89, "2010": 0.9}, "race_black": {"1960": 0.01, "1970": 0.03, "1980": 0.02, "1990": 0.02, "2000": 0.02, "2010": 0.01}, "race_span_hisp": {"1960": 0.02, "1970": 0.06, "1980": 0.03, "1990": 0.04, "2000": 0.06, "2010": 0.07}, "educ_hs": {"1960": 0.87, "1970": 0.92, "1980": 0.95, "1990": 0.93, "2000": 0.96, "2010": 0.96}, "educ_college": {"1960": 0.47, "1970": 0.53, "1980": 0.67, "1990": 0.79, "2000": 0.84, "2010": 0.86}, "educ_bach": {"1990": 0.46, "2000": 0.61, "2010": 0.54}, "jobs_pers_entmt": {"1970": 0.19, "1980": 0.21, "1990": 0.31, "2000": 0.14, "2010": 0.19}, "jobs_service": {"1960": 0.05, "1970": 0.06, "1980": 0.06, "1990": 0.05, "2000": 0.05, "2010": 0.06}, "avg_fam_income": {"1970": 20300.0, "1980": 34700.0, "1990": 122500.0, "2000": 177600.0, "2010": 214500.0}, "med_fam_income": {"1970": 15200.0, "1980": 28500.0, "1990": 72600.0, "2000": 122800.0, "2010": 130500.0}, "rented_housing": {"1960": 0.46, "1970": 0.55, "1980": 0.48, "1990": 0.39, "2000": 0.41, "2010": 0.23}, "foreign_born_pop": {"1970": 0.14, "1980": 0.15, "1990": 0.18, "2000": 0.23, "2010": 0.15}, "foreign_noncitizens": {"1970": 0.05, "1990": 0.07, "2000": 0.11, "2010": 0.05}, "foreign_naturalized": {"1970": 0.09, "1990": 0.1, "2000": 0.12, "2010": 0.05}}, "occupants_data": [{"fragment": "", "year": 1965, "entry": "PLUSH PUP THE"}, {"fragment": "", "year": 1973, "entry": "DUDLEY DO-RIGHT EMPORIUM"}, {"fragment": "", "year": 1987, "entry": "WARD JAY PRODUCTIONS INC"}, {"fragment": "", "year": 1987, "entry": "DUDLEY DO-RIGHT EMPORIUM"}], "newspaper_data": [], "social_cultural_data": [{"source_date": null, "building_date": 1972, "data_type": "Article", "source": "Esotouric", "entry": "Dudley Do-Right's Emporium", "url": "https://esotouric.com/2017/07/25/bullwinkle/"}], "assessor_data": []}