{"side": "n", "boundaries": [97.09155, 97.41832], "photos": [{"id": "943192a7-b696-4b99-ad40-2554ec20032e", "coordinate": 97.3512, "year": 1966}, {"id": "247cbb0d-ab8e-4f95-9e1a-274c21c296cb", "coordinate": 97.41462, "year": 1973}, {"id": "906eeefe-c90a-4e6c-83f6-bfbfd1a4ef4c", "coordinate": 97.28575, "year": 1985}, {"id": "c5c28dcc-f183-4afd-88b6-6cda8f280598", "coordinate": 97.39263, "year": 1995}], "census_data": {"tracts": {"1960": null, "1970": null, "1980": null, "1990": null, "2000": null, "2010": null}}, "occupants_data": [{"fragment": "", "year": 1973, "entry": "THE LOOK"}, {"fragment": "", "year": 1987, "entry": "NOVEX TUXEDO SALES & RENTAL"}], "newspaper_data": [], "social_cultural_data": [], "assessor_data": []}