{"side": "n", "boundaries": [95.21208, 96.33303], "photos": [{"id": "5c186def-37b2-473b-8865-75c5e4639af4", "coordinate": 95.59146, "year": 1966}, {"id": "97fbbb07-90c3-4cf4-8eea-a3b451f01274", "coordinate": 96.0314, "year": 1966}, {"id": "57b703ee-b2c0-48b2-89af-a03b23cc886a", "coordinate": 95.59085, "year": 1966}, {"id": "076204e6-adb3-4d76-9bda-47a5ad1e6e81", "coordinate": 96.26478, "year": 1966}, {"id": "a7f7ef22-c77e-4fd0-97f5-bdeaa4044114", "coordinate": 95.21826, "year": 1973}, {"id": "3e91d9a8-0d21-4f24-8c32-aa7382a9653c", "coordinate": 95.65753, "year": 1973}, {"id": "358d92d8-5c41-4c65-8450-7abadcd199f8", "coordinate": 96.09681, "year": 1973}, {"id": "4045c365-4370-4ee4-924f-783077d7cf16", "coordinate": 95.37376, "year": 1985}, {"id": "c7178fb2-fbaa-4158-b2b2-f371b514540e", "coordinate": 95.85176, "year": 1985}, {"id": "377c266d-3077-4fd3-9200-6ae47bf8e3bc", "coordinate": 96.32976, "year": 1985}, {"id": "03f278fe-cb68-4a64-a21c-9a53e50b0f42", "coordinate": 95.74117, "year": 1995}, {"id": "b4578cb4-6c65-4667-8628-81766df0b53c", "coordinate": 95.38663, "year": 1995}, {"id": "31be1a34-e38e-4b90-8c0e-1c61d163bc2e", "coordinate": 95.88813, "year": 1995}, {"id": "c03c19fc-d872-4a2c-aafe-8b63ebbb5186", "coordinate": 95.7568, "year": 2007}, {"id": "d18338ee-49eb-4349-a5c8-678d0f8d8986", "coordinate": 96.32337, "year": 2007}, {"id": "7d57056e-320e-43bd-aa2f-9a8e9ef53d71", "coordinate": 95.66182, "year": 2007}, {"id": "6e5ce2c5-48bf-4261-9dda-95d75e1d45d4", "coordinate": 96.29738, "year": 2007}], "census_data": {"tracts": {"1960": null, "1970": null, "1980": null, "1990": null, "2000": null, "2010": null}}, "occupants_data": [{"fragment": "", "year": 1973, "entry": "KINGS CELLAR INC"}, {"fragment": "", "year": 1987, "entry": "KING'S CELLAR LIQUOR"}], "newspaper_data": [{"title": "Art Tower Started As Vietnam Protest", "date": {"year": 1966, "month": 1, "day": 28}, "source": "Los Angeles Times", "entry": "On January 28, 1966, the Los Angeles Times reported on the construction underway at the intersection of Sunset Boulevard and La Cienega Boulevard of a 65-foot steel tower designed as a protest against the Vietnam War. The tower was sponsored by the Artists Protest Committee, an international group of artists who were \u201cagainst war and for peace,\u201d and designed by New York sculptor Mark Di Suvero. The committee explained why the tower was being built: \u201cIt is no longer possible to work in peace.\u201d", "url": ""}], "social_cultural_data": [], "assessor_data": []}