{"side": "n", "boundaries": [80.723, 82.44205], "photos": [{"id": "cf8cbf82-8d8b-4c18-b2fe-71c0f234e191", "coordinate": 80.87115, "year": 1966}, {"id": "ea566ed1-2881-4ff8-8e2f-98a77fb84a35", "coordinate": 81.23996, "year": 1966}, {"id": "64558fe6-ffab-4957-8784-a8b02c21733f", "coordinate": 81.60878, "year": 1966}, {"id": "332e502f-e1ad-4c48-823f-d7668173a248", "coordinate": 81.9776, "year": 1966}, {"id": "75bf5ad3-6ecb-499e-a1c3-887c4d840fb7", "coordinate": 82.34641, "year": 1966}, {"id": "a5f2f237-e4bd-4e96-be63-321cea6729cb", "coordinate": 80.83396, "year": 1966}, {"id": "eaa2f654-7ac1-4147-9fd2-18f759783920", "coordinate": 81.23905, "year": 1966}, {"id": "fcbc53e4-bbe8-419a-be24-d6897c273259", "coordinate": 81.64414, "year": 1966}, {"id": "c153ecf9-4830-4460-a6c1-ed6e1a7a4876", "coordinate": 82.04923, "year": 1966}, {"id": "ef181e59-4689-41b5-abab-ecee0ec5a374", "coordinate": 80.8291, "year": 1973}, {"id": "ab45ef8e-9860-4052-a63c-e8d6a0508545", "coordinate": 81.28025, "year": 1973}, {"id": "e6256e16-83f8-4868-bf50-6c6a5ad677f5", "coordinate": 81.73139, "year": 1973}, {"id": "4ae47a4e-f5b1-4c59-bb49-17a0e916bec0", "coordinate": 82.18254, "year": 1973}, {"id": "0b55a2d3-6afd-475e-93c4-09f12ac9bd76", "coordinate": 80.80353, "year": 1985}, {"id": "0bfdd13c-0525-43aa-9143-356495397000", "coordinate": 81.21614, "year": 1985}, {"id": "44be23ee-6861-40e4-aeaf-1ca3c25173dc", "coordinate": 81.63197, "year": 1985}, {"id": "189bd313-b108-4133-b886-873426e4a7ec", "coordinate": 82.0478, "year": 1985}, {"id": "a608f431-2549-41e9-ba0f-d105b515eb4f", "coordinate": 80.92608, "year": 1995}, {"id": "30fad2cb-8a42-4f32-803a-aecb29cf7ce8", "coordinate": 81.47646, "year": 1995}, {"id": "2fc68f71-793e-4c9b-83d3-5a3808374cde", "coordinate": 82.02685, "year": 1995}, {"id": "30a8a616-c7f6-4778-9ef9-e49de505fa80", "coordinate": 80.89722, "year": 2007}, {"id": "55a2480d-23db-41ed-8e45-9eec1e66dbb6", "coordinate": 81.4969, "year": 2007}, {"id": "0ce1a234-ae89-4296-a5aa-d6f6bff75f84", "coordinate": 82.09658, "year": 2007}], "census_data": {"tracts": {"1960": 7005, "1970": 7005, "1980": 7005, "1990": 7005, "2000": 7005, "2010": 7005.02}, "total_pop": {"1960": 5187.0, "1970": 5125.0, "1980": 7469.0, "1990": 7715.0, "2000": 7994.0, "2010": 4246.0}, "race_white": {"1960": 0.99, "1970": 0.95, "1980": 0.9, "1990": 0.9, "2000": 0.86, "2010": 0.87}, "race_black": {"1960": 0.004, "1970": 0.02, "1980": 0.05, "1990": 0.04, "2000": 0.03, "2010": 0.05}, "race_span_hisp": {"1960": 0.04, "1970": 0.07, "1980": 0.06, "1990": 0.07, "2000": 0.08, "2010": 0.11}, "educ_hs": {"1960": 0.83, "1970": 0.92, "1980": 0.96, "1990": 0.91, "2000": 0.95, "2010": 0.97}, "educ_college": {"1960": 0.38, "1970": 0.45, "1980": 0.64, "1990": 0.76, "2000": 0.82, "2010": 0.86}, "educ_bach": {"1990": 0.47, "2000": 0.53, "2010": 0.57}, "jobs_pers_entmt": {"1970": 0.19, "1980": 0.16, "1990": 0.24, "2000": 0.13, "2010": 0.18}, "jobs_service": {"1960": 0.1, "1970": 0.1, "1980": 0.1, "1990": 0.12, "2000": 0.14, "2010": 0.14}, "avg_fam_income": {"1970": 24300.0, "1980": 25500.0, "1990": 75800.0, "2000": 93300.0, "2010": 111300.0}, "med_fam_income": {"1980": 22200.0, "1990": 48000.0, "2000": 69000.0, "2010": 71600.0}, "rented_housing": {"1960": 0.8, "1970": 0.9, "1980": 0.8, "1990": 0.61, "2000": 0.64, "2010": 0.64}, "foreign_born_pop": {"1970": 0.19, "1980": 0.21, "1990": 0.22, "2000": 0.25, "2010": 0.3}, "foreign_noncitizens": {"1970": 0.08, "1990": 0.12, "2000": 0.12, "2010": 0.14}, "foreign_naturalized": {"1970": 0.11, "1990": 0.1, "2000": 0.13, "2010": 0.16}}, "occupants_data": [{"fragment": "", "year": 1987, "entry": "YOGURT DELITE"}, {"fragment": "", "year": 1987, "entry": "OPTICAL OUTLOOK"}, {"fragment": "", "year": 1987, "entry": "WIZARD THE"}, {"fragment": "B", "year": 1987, "entry": "CALIF FOOD STORES"}, {"fragment": "C", "year": 1987, "entry": "ELITE CLEANERS"}], "newspaper_data": [], "social_cultural_data": [], "assessor_data": [{"id": 1011, "order": "1011.00000000000000000000", "OBJECTID": "1326656", "AIN": "5559019026", "APN": "5559-019-026", "address": "8555", "SitusDirection": "W", "fragment": "", "SitusStreet": "SUNSET BLVD", "SitusAddress": "8555 W SUNSET BLVD", "SitusCity": "WEST HOLLYWOOD CA", "SitusZIP": "90069-2353", "SitusFullAddress": "8555 W SUNSET BLVD WEST HOLLYWOOD CA 90069", "TaxRateArea": "1349", "TaxRateCity": "WEST HOLLYWOOD", "AgencyClassNo": "", "AgencyName": "", "AgencyType": "", "UseCode": "1500", "UseCode_2": "15", "UseType": "Commercial", "UseDescription": "Shopping Centers (Neighborhood, community)", "DesignType1": "1101", "YearBuilt1": "1977", "EffectiveYear1": "1977", "Units1": "0", "Bedrooms1": "0", "Bathrooms1": "0", "SQFTmain1": "6100", "DesignType2": "", "YearBuilt2": "", "EffectiveYear2": "", "Units2": "", "Bedrooms2": "", "Bathrooms2": "", "SQFTmain2": "", "DesignType3": "", "YearBuilt3": "", "EffectiveYear3": "", "Units3": "", "Bedrooms3": "", "Bathrooms3": "", "SQFTmain3": "", "DesignType4": "", "YearBuilt4": "", "EffectiveYear4": "", "Units4": "", "Bedrooms4": "", "Bathrooms4": "", "SQFTmain4": "", "DesignType5": "", "YearBuilt5": "", "EffectiveYear5": "", "Units5": "", "Bedrooms5": "", "Bathrooms5": "", "SQFTmain5": "", "Roll_Year": "2021", "Roll_LandValue": "2167131", "Roll_ImpValue": "520098", "Roll_PersPropValue": "0", "Roll_FixtureValue": "0", "Roll_HomeOwnersExemp": "0", "Roll_RealEstateExemp": "0", "Roll_PersPropExemp": "0", "Roll_FixtureExemp": "0", "Roll_LandBaseYear": "1989", "Roll_ImpBaseYear": "1989", "SpatialChangeDate": "", "ParcelCreateDate": "0", "ParcelTypeCode": "0", "Assr_Map": "5559-019", "Assr_Index_Map": "5559-NDX", "QualityClass1": "C65D", "QualityClass2": "", "QualityClass3": "", "QualityClass4": "", "QualityClass5": "", "LegalDescLine1": "*TR=10805*LOT COM AT MOST E COR OF LOT", "LegalDescLine2": "B PM 95-48-49 TH S 38\u00ac\u00a237' E TO NW LINE", "LegalDescLine3": "OF SUNSET BLVD TH SW THEREON AND NW ON", "LegalDescLine4": "NE LINE OF LONDONDERRY PL TO SE LINE OF", "LegalDescLine5": "SD PM TH NE THEREON TO BEG  POR OF LOTS", "LegalDescLineLast": "1 AND LOT    4", "LegalDescription": "*TR=10805*LOT COM AT MOST E COR OF LOT B PM 95-48-49 TH S 38\u00ac\u00a237' E TO NW LINE OF SUNSET BLVD TH SW THEREON AND NW ON NE LINE OF LONDONDERRY PL TO SE LINE OF SD PM TH NE THEREON TO BEG  POR OF LOTS 1 AND LOT    4"}]}